setup.py
seen/__init__.py
seen/asrequests.py
seen/browser_response.py
seen/fetch.py
seen/fetch_by_browser.py
seen/item.py
seen/logger.py
seen/parser.py
seen/selector.py
seen/spider.py
seen.egg-info/PKG-INFO
seen.egg-info/SOURCES.txt
seen.egg-info/dependency_links.txt
seen.egg-info/requires.txt
seen.egg-info/top_level.txt